pyside6_drawer/__init__.py
pyside6_drawer/drawer.py
pyside6_drawer/resources/__init__.py
pyside6_drawer-0.0.1.dist-info/LICENSE
pyside6_drawer-0.0.1.dist-info/METADATA
pyside6_drawer-0.0.1.dist-info/WHEEL
pyside6_drawer-0.0.1.dist-info/top_level.txt
pyside6_drawer-0.0.1.dist-info/RECORD
