Metadata-Version: 2.1
Name: pyside6-drawer
Version: 0.0.1
Summary: PySide6 drawer
Home-page: https://github.com/sw22m/PySide6-Drawer.git
Author: Simon Wu
Author-email: simonwu22@outlook.com
License: MIT
License-File: LICENSE
Requires-Dist: PySide6
